[
{"Company": "Coralogix", "Revenue": "<p> <!-- -->$36M<!-- --> </p>", "Funding": "<p> <!-- -->$236.5M<!-- --> </p>"},
{"Company": "Paddle", "Revenue": "<p> <!-- -->$55M<!-- --> </p>", "Funding": "<p> <!-- -->$293.3M<!-- --> </p>"},
{"Company": "Hotjar", "Revenue": "<p> <!-- -->$25M<!-- --> </p>", "Funding": null},
{"Company": "ClickUp", "Revenue": "<p> <!-- -->$80M<!-- --> </p>", "Funding": "<p> <!-- -->$537.5M<!-- --> </p>"},
{"Company": "SecurityScorecard", "Revenue": "<p> <!-- -->$71M<!-- --> </p>", "Funding": "<p> <!-- -->$293.4M<!-- --> </p>"},
{"Company": "Lemlist", "Revenue": "<p> <!-- -->$10M<!-- --> </p>", "Funding": "<p> <!-- -->$30M<!-- --> </p>"},
{"Company": "Copado", "Revenue": "<p> <!-- -->$52M<!-- --> </p>", "Funding": "<p> <!-- -->$278M<!-- --> </p>"},
{"Company": "ProfitWell", "Revenue": "<p> <!-- -->$22M<!-- --> </p>", "Funding": null},
{"Company": "Mindee", "Revenue": "<p> <!-- -->$1.4M<!-- --> </p>", "Funding": "<p> <!-- -->$16.2M<!-- --> </p>"},
{"Company": "Cloudbeds", "Revenue": "<p> <!-- -->$30M<!-- --> </p>", "Funding": "<p> <!-- -->$248.4M<!-- --> </p>"},
{"Company": "Chili Piper", "Revenue": "<p> <!-- -->$16.2M<!-- --> </p>", "Funding": "<p> <!-- -->$58M<!-- --> </p>"},
{"Company": "Hopin", "Revenue": "<p> <!-- -->$100M<!-- --> </p>", "Funding": "<p> <!-- -->$1B<!-- --> </p>"},
{"Company": "Gong", "Revenue": "<p> <!-- -->$120M<!-- --> </p>", "Funding": "<p> <!-- -->$583M<!-- --> </p>"},
{"Company": "Outreach", "Revenue": "<p> <!-- -->$158M<!-- --> </p>", "Funding": "<p> <!-- -->$488.7M<!-- --> </p>"},
{"Company": "Zenefits", "Revenue": "<p> <!-- -->$100M<!-- --> </p>", "Funding": "<p> <!-- -->$584.1M<!-- --> </p>"},
{"Company": "Zenbusiness", "Revenue": "<p> <!-- -->$45M<!-- --> </p>", "Funding": "<p> <!-- -->$273.1M<!-- --> </p>"},
{"Company": "Acuityscheduling", "Revenue": "<p> <!-- -->$9.6M<!-- --> </p>", "Funding": null},
{"Company": "WriterAccess", "Revenue": "<p> <!-- -->$9.4M<!-- --> </p>", "Funding": null},
{"Company": "Deckrobot Inc,DeckRobot", "Revenue": "<p> <!-- -->$1.1M<!-- --> </p>", "Funding": "<p> <!-- -->$2.5M<!-- --> </p>"},
{"Company": "Docsend", "Revenue": "<p> <!-- -->$9.2M<!-- --> </p>", "Funding": "<p> <!-- -->$14.7M<!-- --> </p>"},
{"Company": "247 ai", "Revenue": "<p> <!-- -->$306M<!-- --> </p>", "Funding": "<p> <!-- -->$22M<!-- --> </p>"},
{"Company": "Freshworks", "Revenue": "<p> <!-- -->$337.8M<!-- --> </p>", "Funding": "<p> <!-- -->$1.5B<!-- --> </p>"},
{"Company": "Numerated", "Revenue": "<p> <!-- -->$26M<!-- --> </p>", "Funding": "<p> <!-- -->$27.5M<!-- --> </p>"},
{"Company": "DesignPickle", "Revenue": "<p> <!-- -->$21.1M<!-- --> </p>", "Funding": "<p> <!-- -->$249.5K<!-- --> </p>"},
{"Company": "Handshake", "Revenue": "<p> <!-- -->$20M<!-- --> </p>", "Funding": "<p> <!-- -->$23.5M<!-- --> </p>"},
{"Company": "Qualified", "Revenue": "<p> <!-- -->$2.5M<!-- --> </p>", "Funding": null},
{"Company": "Printful", "Revenue": "<p> <!-- -->$150M<!-- --> </p>", "Funding": "<p> <!-- -->$130M<!-- --> </p>"},
{"Company": "Sprig", "Revenue": "<p> <!-- -->$6.5M<!-- --> </p>", "Funding": "<p> <!-- -->$58M<!-- --> </p>"},
{"Company": "Nutshell", "Revenue": "<p> <!-- -->$4.7M<!-- --> </p>", "Funding": "<p> <!-- -->$750K<!-- --> </p>"},
{"Company": "Buzzilla", "Revenue": "<p> <!-- -->$4.8M<!-- --> </p>", "Funding": "<p> <!-- -->$1M<!-- --> </p>"},
{"Company": "Ringlead", "Revenue": "<p> <!-- -->$6M<!-- --> </p>", "Funding": "<p> <!-- -->$1.3M<!-- --> </p>"},
{"Company": "Lucidworks", "Revenue": "<p> <!-- -->$48M<!-- --> </p>", "Funding": "<p> <!-- -->$203M<!-- --> </p>"},
{"Company": "Softr", "Revenue": "<p> <!-- -->$276K<!-- --> </p>", "Funding": "<p> <!-- -->$15.7M<!-- --> </p>"},
{"Company": "Ubeeko", "Revenue": "<p> <!-- -->$337.3K<!-- --> </p>", "Funding": null},
{"Company": "CamBioScience", "Revenue": "<p> <!-- -->$664K<!-- --> </p>", "Funding": "<p> <!-- -->$4.6M<!-- --> </p>"},
{"Company": "agreement24 avtal24", "Revenue": "<p> <!-- -->$62.5K<!-- --> </p>", "Funding": null},
{"Company": "Rickshaw", "Revenue": "<p> <!-- -->$423.8K<!-- --> </p>", "Funding": null},
{"Company": "Conifer Labs", "Revenue": "<p> <!-- -->$292.6K<!-- --> </p>", "Funding": null},
{"Company": "GlobalSight", "Revenue": "<p> <!-- -->$114.8K<!-- --> </p>", "Funding": null},
{"Company": "10Duke", "Revenue": "<p> <!-- -->$1.1M<!-- --> </p>", "Funding": null},
{"Company": "Start Studio", "Revenue": "<p> <!-- -->$628.5K<!-- --> </p>", "Funding": null},
{"Company": "Twenix", "Revenue": "<p> <!-- -->$960.1K<!-- --> </p>", "Funding": "<p> <!-- -->$1.2M<!-- --> </p>"},
{"Company": "Verse Solutions", "Revenue": "<p> <!-- -->$234.3K<!-- --> </p>", "Funding": null},
{"Company": "Element", "Revenue": "<p> <!-- -->$1.4M<!-- --> </p>", "Funding": "<p> <!-- -->$18.1M<!-- --> </p>"},
{"Company": "iTeh", "Revenue": "<p> <!-- -->$243.9K<!-- --> </p>", "Funding": null},
{"Company": "ERUDIT AI", "Revenue": "<p> <!-- -->$763.5K<!-- --> </p>", "Funding": "<p> <!-- -->$5.1M<!-- --> </p>"},
{"Company": "Photography BlogSites", "Revenue": "<p> <!-- -->$1.9M<!-- --> </p>", "Funding": null},
{"Company": "BECS", "Revenue": "<p> <!-- -->$3.6M<!-- --> </p>", "Funding": "<p> <!-- -->$3.2M<!-- --> </p>"},
{"Company": "Yardstick Software", "Revenue": "<p> <!-- -->$1.8M<!-- --> </p>", "Funding": null},
{"Company": "Mansion Ecommerce", "Revenue": "<p> <!-- -->$51.5K<!-- --> </p>", "Funding": null},
{"Company": "Coralogix", "Revenue": "<p> <!-- -->$36M<!-- --> </p>", "Funding": "<p> <!-- -->$236.5M<!-- --> </p>"},
{"Company": "Paddle", "Revenue": "<p> <!-- -->$55M<!-- --> </p>", "Funding": "<p> <!-- -->$293.3M<!-- --> </p>"},
{"Company": "Hotjar", "Revenue": "<p> <!-- -->$25M<!-- --> </p>", "Funding": null},
{"Company": "ClickUp", "Revenue": "<p> <!-- -->$80M<!-- --> </p>", "Funding": "<p> <!-- -->$537.5M<!-- --> </p>"},
{"Company": "SecurityScorecard", "Revenue": "<p> <!-- -->$71M<!-- --> </p>", "Funding": "<p> <!-- -->$293.4M<!-- --> </p>"},
{"Company": "Lemlist", "Revenue": "<p> <!-- -->$10M<!-- --> </p>", "Funding": "<p> <!-- -->$30M<!-- --> </p>"},
{"Company": "Copado", "Revenue": "<p> <!-- -->$52M<!-- --> </p>", "Funding": "<p> <!-- -->$278M<!-- --> </p>"},
{"Company": "ProfitWell", "Revenue": "<p> <!-- -->$22M<!-- --> </p>", "Funding": null},
{"Company": "Mindee", "Revenue": "<p> <!-- -->$1.4M<!-- --> </p>", "Funding": "<p> <!-- -->$16.2M<!-- --> </p>"},
{"Company": "Cloudbeds", "Revenue": "<p> <!-- -->$30M<!-- --> </p>", "Funding": "<p> <!-- -->$248.4M<!-- --> </p>"},
{"Company": "Chili Piper", "Revenue": "<p> <!-- -->$16.2M<!-- --> </p>", "Funding": "<p> <!-- -->$58M<!-- --> </p>"},
{"Company": "Hopin", "Revenue": "<p> <!-- -->$100M<!-- --> </p>", "Funding": "<p> <!-- -->$1B<!-- --> </p>"},
{"Company": "Gong", "Revenue": "<p> <!-- -->$120M<!-- --> </p>", "Funding": "<p> <!-- -->$583M<!-- --> </p>"},
{"Company": "Outreach", "Revenue": "<p> <!-- -->$158M<!-- --> </p>", "Funding": "<p> <!-- -->$488.7M<!-- --> </p>"},
{"Company": "Zenefits", "Revenue": "<p> <!-- -->$100M<!-- --> </p>", "Funding": "<p> <!-- -->$584.1M<!-- --> </p>"},
{"Company": "Zenbusiness", "Revenue": "<p> <!-- -->$45M<!-- --> </p>", "Funding": "<p> <!-- -->$273.1M<!-- --> </p>"},
{"Company": "Acuityscheduling", "Revenue": "<p> <!-- -->$9.6M<!-- --> </p>", "Funding": null},
{"Company": "WriterAccess", "Revenue": "<p> <!-- -->$9.4M<!-- --> </p>", "Funding": null},
{"Company": "Deckrobot Inc,DeckRobot", "Revenue": "<p> <!-- -->$1.1M<!-- --> </p>", "Funding": "<p> <!-- -->$2.5M<!-- --> </p>"},
{"Company": "Docsend", "Revenue": "<p> <!-- -->$9.2M<!-- --> </p>", "Funding": "<p> <!-- -->$14.7M<!-- --> </p>"},
{"Company": "247 ai", "Revenue": "<p> <!-- -->$306M<!-- --> </p>", "Funding": "<p> <!-- -->$22M<!-- --> </p>"},
{"Company": "Freshworks", "Revenue": "<p> <!-- -->$337.8M<!-- --> </p>", "Funding": "<p> <!-- -->$1.5B<!-- --> </p>"},
{"Company": "Numerated", "Revenue": "<p> <!-- -->$26M<!-- --> </p>", "Funding": "<p> <!-- -->$27.5M<!-- --> </p>"},
{"Company": "DesignPickle", "Revenue": "<p> <!-- -->$21.1M<!-- --> </p>", "Funding": "<p> <!-- -->$249.5K<!-- --> </p>"},
{"Company": "Handshake", "Revenue": "<p> <!-- -->$20M<!-- --> </p>", "Funding": "<p> <!-- -->$23.5M<!-- --> </p>"}
]